mathrender/__init__.py
mathrender/cli.py
mathrender/converter.py
mathrender/mime_builder.py
mathrender/rich_clipboard.py
mathrender/sendgrid_sender.py
mathrender/simple_gmail.py
mathrender/smtp_sender.py
mathrender-0.1.1.dist-info/LICENSE
mathrender-0.1.1.dist-info/METADATA
mathrender-0.1.1.dist-info/WHEEL
mathrender-0.1.1.dist-info/entry_points.txt
mathrender-0.1.1.dist-info/RECORD
