Metadata-Version: 2.1
Name: mathrender
Version: 0.1.1
Summary: Convert LaTeX mathematical expressions to images for web and email
License: MIT
Author: Francisco Boerr
Author-email: francisco.boerr@deinnovatie.com
Requires-Python: >=3.8.1,<4.0.0
Classifier: License :: OSI Approved :: MIT License
Classifier: Programming Language :: Python :: 3
Classifier: Programming Language :: Python :: 3.9
Classifier: Programming Language :: Python :: 3.10
Classifier: Programming Language :: Python :: 3.11
Classifier: Programming Language :: Python :: 3.12
Provides-Extra: clipboard
Requires-Dist: click (>=8.1.0,<9.0.0)
Requires-Dist: jinja2 (>=3.1.0,<4.0.0)
Requires-Dist: pillow (>=10.0.0,<11.0.0)
Requires-Dist: pyperclip (>=1.8.0,<2.0.0) ; extra == "clipboard"
Requires-Dist: pywin32 (>=306,<307) ; (sys_platform == "win32") and (extra == "clipboard")
